asyncebay/__init__.py
asyncebay/config.py
asyncebay/ebay_caller.py
asyncebay/request_builder.py
AsynceBay-1.0.0.dist-info/LICENSE
AsynceBay-1.0.0.dist-info/METADATA
AsynceBay-1.0.0.dist-info/WHEEL
AsynceBay-1.0.0.dist-info/top_level.txt
AsynceBay-1.0.0.dist-info/RECORD
