Metadata-Version: 2.1
Name: AsynceBay
Version: 1.0.0
Summary: An Asynchronous wrapper/interface for the eBayAPI
Home-page: https://github.com/Ywacch/AsynceBay
Author: Emmanuel Adebayo
Author-email: toluwalashe.adebayo@gmail.com
License: MIT
Platform: UNKNOWN
License-File: LICENSE
Requires-Dist: aiohttp
